README.rst
setup.cfg
setup.py
src/pisurvl/__init__.py
src/pisurvl/app.py
src/pisurvl/exceptions.py
src/pisurvl/main.py
src/pisurvl/settings.py
src/pisurvl.egg-info/PKG-INFO
src/pisurvl.egg-info/SOURCES.txt
src/pisurvl.egg-info/dependency_links.txt
src/pisurvl.egg-info/entry_points.txt
src/pisurvl.egg-info/requires.txt
src/pisurvl.egg-info/top_level.txt
src/pisurvl/camera/__init__.py
src/pisurvl/camera/camera.py
src/pisurvl/camera/factory.py
src/pisurvl/camera/opencv.py
src/pisurvl/exectools/__init__.py
src/pisurvl/exectools/exectools.py
src/pisurvl/google/__init__.py
src/pisurvl/google/credentials.py
src/pisurvl/google/drive.py
src/pisurvl/google/mail.py
src/pisurvl/infrastructure/__init__.py
src/pisurvl/infrastructure/date_provider.py
src/pisurvl/messaging/__init__.py
src/pisurvl/messaging/command_listener.py
src/pisurvl/messaging/naming.py
src/pisurvl/messaging/request_processor.py
src/pisurvl/messaging/response_processor.py
src/pisurvl/motion/__init__.py
src/pisurvl/motion/detection.py
src/pisurvl/motion/inspector.py
src/pisurvl/surveil/__init__.py
src/pisurvl/surveil/backup.py
src/pisurvl/surveil/event_notifier.py
src/pisurvl/surveil/surveil.py